formatdoc/__init__.py
formatdoc/cli.py
formatdoc-0.1.dist-info/licenses/LICENSE
formatdoc-0.1.dist-info/METADATA
formatdoc-0.1.dist-info/WHEEL
formatdoc-0.1.dist-info/entry_points.txt
formatdoc-0.1.dist-info/top_level.txt
formatdoc-0.1.dist-info/RECORD
