Metadata-Version: 2.4
Name: formatdoc
Version: 0.1
License-File: LICENSE
Requires-Dist: python-docx
Dynamic: license-file
Dynamic: requires-dist
